ajaximage/__init__.py
ajaximage/admin.py
ajaximage/apps.py
ajaximage/fields.py
ajaximage/forms.py
ajaximage/models.py
ajaximage/tests.py
ajaximage/urls.py
ajaximage/views.py
ajaximage/widgets.py
ajaximage/static/ajaximage/css/bootstrap-progress.min.css
ajaximage/static/ajaximage/css/styles.css
ajaximage/static/ajaximage/js/ajaximage.js
ajaximage/static/dropzone/css/basic.css
ajaximage/static/dropzone/css/basic.min.css
ajaximage/static/dropzone/css/dropzone.css
ajaximage/static/dropzone/css/dropzone.min.css
ajaximage/static/dropzone/js/dropzone.js
ajaximage/static/dropzone/js/dropzone.min.js
ajaximage/templates/ajaximage/change_form.html
ajaximage/templates/ajaximage/tabular.html
ajaximage/templatetags/__init__.py
ajaximage/templatetags/ajaximage_filters.py
django_ajax_image_upload-0.8.2.dist-info/DESCRIPTION.rst
django_ajax_image_upload-0.8.2.dist-info/METADATA
django_ajax_image_upload-0.8.2.dist-info/RECORD
django_ajax_image_upload-0.8.2.dist-info/WHEEL
django_ajax_image_upload-0.8.2.dist-info/metadata.json
django_ajax_image_upload-0.8.2.dist-info/top_level.txt
