Metadata-Version: 2.0
Name: django-ajax-image-upload
Version: 0.8.2
Summary: Upload images via ajax.
Home-page: https://github.com/idaproject/django-ajax-image-upload
Author: Alexander Temnikov
Author-email: alexander.temnikov@me.com
License: MIT
Keywords: django-ajax-image-upload
Platform: UNKNOWN
Classifier: Development Status :: 3 - Alpha
Classifier: Framework :: Django
Classifier: Framework :: Django :: 1.8
Classifier: Framework :: Django :: 1.9
Classifier: Framework :: Django :: 1.10
Classifier: Framework :: Django :: 2.0
Classifier: Intended Audience :: Developers
Classifier: License :: OSI Approved :: BSD License
Classifier: Natural Language :: English
Classifier: Programming Language :: Python :: 3
Classifier: Programming Language :: Python :: 3.3
Classifier: Programming Language :: Python :: 3.4
Classifier: Programming Language :: Python :: 3.5
Classifier: Programming Language :: Python :: 3.6
Requires-Dist: Django
